<?xml version="1.0" encoding="utf-8" standalone="yes"?>
<!--Configuraciòn dispositivos-->
<Devices>
  <Device>
    <DeviceKey>NTIrr4GA2QdxfJqDc/4jIFzH7ueVA+Fw5Vh0wTBBLA4=</DeviceKey>
    <DeviceName>NHJAX-MID-113C</DeviceName>
    <DeviceID>2</DeviceID>
    <IotHubUri>nhjaxiot.azure-devices.net</IotHubUri>
    <ReadingInterval>30000</ReadingInterval>
    <Ambiente>Room MID 113C</Ambiente>
  </Device>
<Device>
    <DeviceKey>NTIrr4GA2QdxfJqDc/4jIFzH7ueVA+Fw5Vh0wTBBLA4=</DeviceKey>
    <DeviceName>nhjaxcomputerroom</DeviceName>
    <DeviceID>3</DeviceID>
    <IotHubUri>nhjaxiot.azure-devices.net</IotHubUri>
    <ReadingInterval>60000</ReadingInterval>
    <Ambiente>NHJAX Computer Room</Ambiente>
  </Device>
</Devices>